azure/mgmt/devspaces/__init__.py
azure/mgmt/devspaces/dev_spaces_management_client.py
azure/mgmt/devspaces/version.py
azure/mgmt/devspaces/models/__init__.py
azure/mgmt/devspaces/models/controller.py
azure/mgmt/devspaces/models/controller_connection_details.py
azure/mgmt/devspaces/models/controller_connection_details_list.py
azure/mgmt/devspaces/models/controller_connection_details_list_py3.py
azure/mgmt/devspaces/models/controller_connection_details_py3.py
azure/mgmt/devspaces/models/controller_paged.py
azure/mgmt/devspaces/models/controller_py3.py
azure/mgmt/devspaces/models/controller_update_parameters.py
azure/mgmt/devspaces/models/controller_update_parameters_py3.py
azure/mgmt/devspaces/models/dev_spaces_management_client_enums.py
azure/mgmt/devspaces/models/error_details.py
azure/mgmt/devspaces/models/error_details_py3.py
azure/mgmt/devspaces/models/error_response.py
azure/mgmt/devspaces/models/error_response_py3.py
azure/mgmt/devspaces/models/kubernetes_connection_details.py
azure/mgmt/devspaces/models/kubernetes_connection_details_py3.py
azure/mgmt/devspaces/models/orchestrator_specific_connection_details.py
azure/mgmt/devspaces/models/orchestrator_specific_connection_details_py3.py
azure/mgmt/devspaces/models/resource.py
azure/mgmt/devspaces/models/resource_provider_operation_definition.py
azure/mgmt/devspaces/models/resource_provider_operation_definition_paged.py
azure/mgmt/devspaces/models/resource_provider_operation_definition_py3.py
azure/mgmt/devspaces/models/resource_provider_operation_display.py
azure/mgmt/devspaces/models/resource_provider_operation_display_py3.py
azure/mgmt/devspaces/models/resource_py3.py
azure/mgmt/devspaces/models/sku.py
azure/mgmt/devspaces/models/sku_py3.py
azure/mgmt/devspaces/models/tracked_resource.py
azure/mgmt/devspaces/models/tracked_resource_py3.py
azure/mgmt/devspaces/operations/__init__.py
azure/mgmt/devspaces/operations/controllers_operations.py
azure_mgmt_devspaces-0.1.0.dist-info/METADATA
azure_mgmt_devspaces-0.1.0.dist-info/RECORD
azure_mgmt_devspaces-0.1.0.dist-info/WHEEL
azure_mgmt_devspaces-0.1.0.dist-info/top_level.txt
